aws/__init__.py
aws/cloudwatch.py
aws/glue.py
aws/lambda_functions.py
aws/s3.py
aws/stepfunctions.py
pnh_ttf-1.0.2.dist-info/LICENSE
pnh_ttf-1.0.2.dist-info/METADATA
pnh_ttf-1.0.2.dist-info/WHEEL
pnh_ttf-1.0.2.dist-info/top_level.txt
pnh_ttf-1.0.2.dist-info/RECORD
