Metadata-Version: 2.1
Name: pnh_ttf
Version: 1.0.2
Summary: Python package to test cloud infrastructure
Author-email: Gert van Rooyen <gert.van.rooyen@noord-holland.nl>, Mohanraj Subburaj <mohanraj.subburaj@xebia.com>
Project-URL: Issues, https://github.com/provincieNH/pnh_terraform_testing_framework/issues
Classifier: Programming Language :: Python :: 3
Classifier: License :: OSI Approved :: MIT License
Classifier: Operating System :: OS Independent
Requires-Python: >=3.8
License-File: LICENSE
